README.rst
pyproject.toml
spydey/__init__.py
spydey/patternize.py
spydey/spider.py
spydey.egg-info/PKG-INFO
spydey.egg-info/SOURCES.txt
spydey.egg-info/dependency_links.txt
spydey.egg-info/entry_points.txt
spydey.egg-info/requires.txt
spydey.egg-info/top_level.txt