Metadata-Version: 2.4
Name: spydey
Version: 0.6.1
Summary: A web spider, useful for link checking, with several recursion strategies.
Author-email: Paul Winkler <slinkp@gmail.com>
License: MIT
Project-URL: Homepage, https://github.com/slinkp/spydey
Project-URL: Repository, https://github.com/slinkp/spydey
Project-URL: Changelog, https://github.com/slinkp/spydey/blob/main/CHANGES.txt
Classifier: Environment :: Console
Classifier: License :: OSI Approved :: MIT License
Classifier: Programming Language :: Python
Classifier: Topic :: Internet :: WWW/HTTP
Classifier: Topic :: Internet :: WWW/HTTP :: Site Management :: Link Checking
Requires-Python: >=3.9
Requires-Dist: setuptools>=79.0.0
Requires-Dist: lxml>=5
Requires-Dist: httplib2>=0.20.1
Provides-Extra: build
Requires-Dist: build>=1.2; extra == "build"
Requires-Dist: docutils; extra == "build"
Provides-Extra: cli
Requires-Dist: fabulous>=0.4.0; extra == "cli"
